azureml/__init__.py
azureml/telemetry/__init__.py
azureml/telemetry/_customtraceback.py
azureml/telemetry/_telemetry_formatter.py
azureml/telemetry/_version.py
azureml/telemetry/activity.py
azureml/telemetry/log_scope.py
azureml/telemetry/loggers.py
azureml/telemetry/logging_handler.py
azureml/telemetry/telemetry.json
azureml/telemetry/contracts/__init__.py
azureml/telemetry/contracts/_event.py
azureml/telemetry/contracts/_extension_fields.py
azureml/telemetry/contracts/_metric.py
azureml/telemetry/contracts/_required_fields.py
azureml/telemetry/contracts/_standard_fields.py
azureml/telemetry/contracts/_telemetry_object_base.py
azureml/telemetry/logger/__init__.py
azureml/telemetry/logger/_abstract_event_logger.py
azureml/telemetry/logger/_applicationinsights_logger.py
azureml/telemetry/logger/_inmemory_event_logger.py
azureml_telemetry-1.60.0.dist-info/licenses/LICENSE.txt
azureml_telemetry-1.60.0.dist-info/METADATA
azureml_telemetry-1.60.0.dist-info/WHEEL
azureml_telemetry-1.60.0.dist-info/top_level.txt
azureml_telemetry-1.60.0.dist-info/RECORD
